area_code_locator/__init__.py
area_code_locator/area_code_locator.py
area_code_locator/cli.py
area_code_locator/data/area-codes.parquet
area_code_locator-0.2.1.dist-info/licenses/LICENSE
area_code_locator-0.2.1.dist-info/METADATA
area_code_locator-0.2.1.dist-info/WHEEL
area_code_locator-0.2.1.dist-info/entry_points.txt
area_code_locator-0.2.1.dist-info/top_level.txt
area_code_locator-0.2.1.dist-info/RECORD
