Metadata-Version: 2.4
Name: area-code-locator
Version: 0.2.1
Summary: Reverse-geocode latitude/longitude to NANP (North American) telephone area codes
Author: Area Code Locator Contributors
License: MIT License
Project-URL: Homepage, https://github.com/Eat-A-Fish/area-code-locator
Project-URL: Repository, https://github.com/Eat-A-Fish/area-code-locator
Project-URL: Issues, https://github.com/Eat-A-Fish/area-code-locator/issues
Keywords: area-code,nanp,north-american-numbering-plan,reverse-geocoding,geopandas,gis,geospatial,telephony,python-package,coordinates,latitude-longitude
Classifier: Development Status :: 4 - Beta
Classifier: Intended Audience :: Developers
Classifier: License :: OSI Approved :: MIT License
Classifier: Operating System :: OS Independent
Classifier: Programming Language :: Python :: 3
Classifier: Programming Language :: Python :: 3.8
Classifier: Programming Language :: Python :: 3.9
Classifier: Programming Language :: Python :: 3.10
Classifier: Programming Language :: Python :: 3.11
Classifier: Programming Language :: Python :: 3.12
Classifier: Topic :: Scientific/Engineering :: GIS
Requires-Python: >=3.8
License-File: LICENSE
Requires-Dist: geopandas>=0.13.0
Requires-Dist: shapely>=2.0.0
Requires-Dist: pyproj>=3.4.0
Requires-Dist: pyarrow>=10.0.0
Requires-Dist: importlib_resources>=5; python_version < "3.9"
Provides-Extra: dev
Requires-Dist: pytest>=7.0.0; extra == "dev"
Requires-Dist: pytest-cov>=4.0.0; extra == "dev"
Dynamic: license-file
